mop/__about__.py
mop/__init__.py
mop/__main__.py
mop/app.py
mop/config.py
mop/core.py
mop/dialogs.py
mop/editorctl.py
mop/filesctl.py
mop/utils.py
Mop-0.1.1.dist-info/AUTHORS.rst
Mop-0.1.1.dist-info/LICENSE
Mop-0.1.1.dist-info/METADATA
Mop-0.1.1.dist-info/WHEEL
Mop-0.1.1.dist-info/entry_points.txt
Mop-0.1.1.dist-info/top_level.txt
Mop-0.1.1.dist-info/RECORD
